src/__init__.py
src/__main__.py
src/api/__init__.py
src/api/oking.py
src/api/okvendas.py
src/api/slack.py
src/api/entities/__init__.py
src/api/entities/cliente.py
src/api/entities/cliente_aprovado.py
src/api/entities/cliente_erp_code.py
src/api/entities/imposto_produto.py
src/api/entities/lista_preco.py
src/api/entities/plano_pagamento_cliente.py
src/api/entities/representante.py
src/database/__init__.py
src/database/connection.py
src/database/queries.py
src/database/sqlserver_db.py
src/database/utils.py
src/database/entities/__init__.py
src/database/entities/client.py
src/database/entities/client_payment_plan.py
src/database/entities/price_list.py
src/database/entities/product_tax.py
src/database/entities/representative.py
src/entities/__init__.py
src/entities/invoice.py
src/entities/log.py
src/entities/order.py
src/entities/orderb2b.py
src/entities/orderb2c.py
src/entities/pagamento.py
src/entities/photos_sku.py
src/entities/price.py
src/entities/product.py
src/entities/response.py
src/entities/tracking.py
src/jobs/__init__.py
src/jobs/client_jobs.py
src/jobs/client_payment_plan_jobs.py
src/jobs/client_payment_plan_semaphore_jobs.py
src/jobs/order_jobs.py
src/jobs/price_jobs.py
src/jobs/products_jobs.py
src/jobs/representative_jobs.py
src/jobs/stock_jobs.py
src/jobs/system_jobs.py
oking_oz-3.2.37.dist-info/LICENSE
oking_oz-3.2.37.dist-info/METADATA
oking_oz-3.2.37.dist-info/WHEEL
oking_oz-3.2.37.dist-info/entry_points.txt
oking_oz-3.2.37.dist-info/top_level.txt
oking_oz-3.2.37.dist-info/RECORD
