Metadata-Version: 2.1
Name: oking-oz
Version: 3.2.37
Summary: Pacote de integração de produtos, preço, estoque e pedidos com o sistema OkVendas da Openk
Author: Openk Tecnologia
Author-email: <suporte.b2c@openk.com.br>
Keywords: python,oking,openk,okvendas,ok
Classifier: Development Status :: 4 - Beta
Classifier: Intended Audience :: Developers
Classifier: Programming Language :: Python :: 3
Classifier: Operating System :: Unix
Classifier: Operating System :: Microsoft :: Windows
License-File: LICENSE
Requires-Dist: mysql-connector-python
Requires-Dist: schedule
Requires-Dist: requests
Requires-Dist: configparser
Requires-Dist: logger
Requires-Dist: cx-Oracle
Requires-Dist: jsonpickle
Requires-Dist: pyodbc
Requires-Dist: pandas
